tipsql/cli/__init__.py
tipsql/cli/__main__.py
tipsql/cli/app.py
tipsql/cli/commands/__init__.py
tipsql/cli/commands/config_jsonschema.py
tipsql/cli/commands/new.py
tipsql/cli/commands/sync.py
tipsql/cli/config/__init__.py
tipsql/cli/config/config.py
tipsql/cli/config/model.py
tipsql/cli/config/v1/__init__.py
tipsql/cli/config/v1/config.py
tipsql/cli/config/v1/formatter/__init__.py
tipsql/cli/config/v1/formatter/ruff_formatter.py
tipsql/cli/exception.py
tipsql/cli/formatter/__init__.py
tipsql/cli/formatter/base_formatter.py
tipsql/cli/formatter/ruff_formatter.py
tipsql/cli/plugins.py
tipsql/cli/prompt/__init__.py
tipsql/cli/prompt/prompt_choice.py
tipsql/cli/prompt/prompt_config.py
tipsql/cli/prompt/prompt_database_type.py
tipsql/cli/utils/__init__.py
tipsql/cli/utils/path.py
tipsql/cli/utils/yaml.py
tipsql_cli-0.0.14.dist-info/METADATA
tipsql_cli-0.0.14.dist-info/WHEEL
tipsql_cli-0.0.14.dist-info/entry_points.txt
tipsql_cli-0.0.14.dist-info/RECORD
