Metadata-Version: 2.1
Name: tipsql-cli
Version: 0.0.14
Summary: tipsql command line interface
Author: yassun7010
Author-email: yassun7010@outlook.com
Requires-Python: >=3.12,<4.0
Classifier: Programming Language :: Python :: 3
Classifier: Programming Language :: Python :: 3.12
Requires-Dist: argcomplete (>=3.1.2,<4.0.0)
Requires-Dist: pydantic (>=2.4.2,<3.0.0)
Requires-Dist: pyyaml (>=6.0.1,<7.0.0)
Requires-Dist: rich (>=13.6.0,<14.0.0)
Requires-Dist: rich-argparse (>=1.3.0,<2.0.0)
Requires-Dist: ruff (>=0.1.4,<0.2.0)
Requires-Dist: tipsql-core (==0.0.14)
